tableschema_ckan_datastore/VERSION
tableschema_ckan_datastore/__init__.py
tableschema_ckan_datastore/mapper.py
tableschema_ckan_datastore/storage.py
tableschema_ckan_datastore/utils.py
tableschema_ckan_datastore-1.1.1.dist-info/LICENSE.md
tableschema_ckan_datastore-1.1.1.dist-info/METADATA
tableschema_ckan_datastore-1.1.1.dist-info/WHEEL
tableschema_ckan_datastore-1.1.1.dist-info/top_level.txt
tableschema_ckan_datastore-1.1.1.dist-info/RECORD
