Metadata-Version: 2.1
Name: tableschema-ckan-datastore
Version: 1.1.1
Summary: Generate CKAN DataStore tables, load and extract data, based on Table Schema descriptors.
Home-page: https://github.com/frictionlessdata/tableschema-ckan-datastore-py
Author: Open Knowledge International
Author-email: info@okfn.org
License: MIT
Keywords: frictionless data,ckan,datastore
Platform: UNKNOWN
Classifier: Development Status :: 4 - Beta
Classifier: Environment :: Web Environment
Classifier: Intended Audience :: Developers
Classifier: License :: OSI Approved :: MIT License
Classifier: Operating System :: OS Independent
Classifier: Programming Language :: Python :: 2
Classifier: Programming Language :: Python :: 2.7
Classifier: Programming Language :: Python :: 3
Classifier: Programming Language :: Python :: 3.3
Classifier: Programming Language :: Python :: 3.4
Classifier: Programming Language :: Python :: 3.5
Classifier: Topic :: Internet :: WWW/HTTP :: Dynamic Content
Classifier: Topic :: Software Development :: Libraries :: Python Modules
Requires-Dist: six (>=1.9)
Requires-Dist: tableschema (>=1.0)
Provides-Extra: develop
Requires-Dist: mock ; extra == 'develop'
Requires-Dist: pylama ; extra == 'develop'
Requires-Dist: pytest ; extra == 'develop'
Requires-Dist: pytest-cov ; extra == 'develop'
Requires-Dist: tox ; extra == 'develop'
Requires-Dist: python-dotenv ; extra == 'develop'
Requires-Dist: requests-mock ; extra == 'develop'
